[{"dt_server":"2024-04-21 09:55:18","dt_tracker":"2024-04-21 09:50:30","lat":"37.86907","lng":"23.743712","altitude":"8","angle":"224","speed":0,"loc_valid":1,"sensors":[],"events":[]},{"dt_server":"2024-04-21 10:53:45","dt_tracker":"2024-04-21 10:48:50","lat":"37.869137","lng":"23.743632","altitude":"16","angle":"185","speed":0,"loc_valid":1,"sensors":[],"events":[]},{"dt_server":"2024-04-21 11:52:11","dt_tracker":"2024-04-21 11:47:10","lat":"37.869155","lng":"23.743752","altitude":"29","angle":"39","speed":0,"loc_valid":1,"sensors":[],"events":[]},{"dt_server":"2024-04-21 12:50:37","dt_tracker":"2024-04-21 12:45:30","lat":"37.869233","lng":"23.743693","altitude":"31","angle":"189","speed":0,"loc_valid":1,"sensors":[],"events":[]},{"dt_server":"2024-04-21 13:49:03","dt_tracker":"2024-04-21 13:43:50","lat":"37.869243","lng":"23.743707","altitude":"24","angle":"150","speed":0,"loc_valid":1,"sensors":[],"events":[]},{"dt_server":"2024-04-21 14:47:29","dt_tracker":"2024-04-21 14:42:10","lat":"37.869165","lng":"23.743647","altitude":"16","angle":"288","speed":0,"loc_valid":1,"sensors":[],"events":[]},{"dt_server":"2024-04-21 15:45:55","dt_tracker":"2024-04-21 15:40:30","lat":"37.869165","lng":"23.743647","altitude":"16","angle":"288","speed":0,"loc_valid":1,"sensors":[],"events":[]},{"dt_server":"2024-04-21 16:44:22","dt_tracker":"2024-04-21 16:38:50","lat":"37.86901","lng":"23.743745","altitude":"0","angle":"335","speed":0,"loc_valid":1,"sensors":[],"events":[]},{"dt_server":"2024-04-21 17:42:48","dt_tracker":"2024-04-21 17:37:10","lat":"37.869075","lng":"23.743742","altitude":"12","angle":"176","speed":0,"loc_valid":1,"sensors":[],"events":[]},{"dt_server":"2024-04-21 18:41:14","dt_tracker":"2024-04-21 18:35:30","lat":"37.869087","lng":"23.743717","altitude":"12","angle":"193","speed":0,"loc_valid":1,"sensors":[],"events":[]},{"dt_server":"2024-04-21 19:39:40","dt_tracker":"2024-04-21 19:33:50","lat":"37.868993","lng":"23.743737","altitude":"6","angle":"147","speed":0,"loc_valid":1,"sensors":[],"events":[]},{"dt_server":"2024-04-21 20:38:06","dt_tracker":"2024-04-21 20:32:10","lat":"37.869155","lng":"23.743702","altitude":"12","angle":"5","speed":0,"loc_valid":1,"sensors":[],"events":[]},{"dt_server":"2024-04-21 21:36:32","dt_tracker":"2024-04-21 21:30:30","lat":"37.869083","lng":"23.743667","altitude":"19","angle":"215","speed":0,"loc_valid":1,"sensors":[],"events":[]}]