[{"dt_server":"2024-05-18 09:10:46","dt_tracker":"2024-05-18 09:09:04","lat":"37.869078","lng":"23.743705","altitude":"12","angle":"11","speed":0,"loc_valid":1,"sensors":[],"events":[]},{"dt_server":"2024-05-18 10:09:12","dt_tracker":"2024-05-18 10:07:24","lat":"37.869078","lng":"23.743705","altitude":"12","angle":"11","speed":0,"loc_valid":1,"sensors":[],"events":[]},{"dt_server":"2024-05-18 11:07:38","dt_tracker":"2024-05-18 11:05:44","lat":"37.869135","lng":"23.743642","altitude":"10","angle":"175","speed":0,"loc_valid":1,"sensors":[],"events":[]},{"dt_server":"2024-05-18 12:06:04","dt_tracker":"2024-05-18 12:04:04","lat":"37.86913","lng":"23.743638","altitude":"14","angle":"358","speed":0,"loc_valid":1,"sensors":[],"events":[]},{"dt_server":"2024-05-18 13:04:30","dt_tracker":"2024-05-18 13:02:24","lat":"37.86913","lng":"23.743638","altitude":"14","angle":"358","speed":0,"loc_valid":1,"sensors":[],"events":[]},{"dt_server":"2024-05-18 14:02:56","dt_tracker":"2024-05-18 14:00:44","lat":"37.869115","lng":"23.743625","altitude":"5","angle":"222","speed":0,"loc_valid":1,"sensors":[],"events":[]},{"dt_server":"2024-05-18 15:01:22","dt_tracker":"2024-05-18 14:59:04","lat":"37.869112","lng":"23.743622","altitude":"12","angle":"350","speed":0,"loc_valid":1,"sensors":[],"events":[]},{"dt_server":"2024-05-18 15:59:49","dt_tracker":"2024-05-18 15:57:24","lat":"37.869067","lng":"23.743722","altitude":"18","angle":"309","speed":0,"loc_valid":1,"sensors":[],"events":[]},{"dt_server":"2024-05-18 16:58:15","dt_tracker":"2024-05-18 16:55:44","lat":"37.869067","lng":"23.743722","altitude":"18","angle":"309","speed":0,"loc_valid":1,"sensors":[],"events":[]},{"dt_server":"2024-05-18 17:56:41","dt_tracker":"2024-05-18 17:54:04","lat":"37.869067","lng":"23.743722","altitude":"18","angle":"309","speed":0,"loc_valid":1,"sensors":[],"events":[]},{"dt_server":"2024-05-18 18:55:07","dt_tracker":"2024-05-18 18:52:24","lat":"37.869137","lng":"23.743648","altitude":"16","angle":"184","speed":0,"loc_valid":1,"sensors":[],"events":[]},{"dt_server":"2024-05-18 19:53:34","dt_tracker":"2024-05-18 19:50:44","lat":"37.869053","lng":"23.743697","altitude":"7","angle":"12","speed":0,"loc_valid":1,"sensors":[],"events":[]},{"dt_server":"2024-05-18 20:52:00","dt_tracker":"2024-05-18 20:49:04","lat":"37.869053","lng":"23.743697","altitude":"7","angle":"12","speed":0,"loc_valid":1,"sensors":[],"events":[]},{"dt_server":"2024-05-18 21:50:26","dt_tracker":"2024-05-18 21:47:24","lat":"37.869003","lng":"23.743608","altitude":"32","angle":"148","speed":0,"loc_valid":1,"sensors":[],"events":[]}]